sgr_library/EI4_ModbusTCP.py
sgr_library/EI4_RestAPI_xsdata.py
sgr_library/__init__.py
sgr_library/generic_interface.py
sgr_library/introspective-reader-CEM.py
sgr_library/payload_decoder.py
sgr_library/smartGridReadyPythonLibrary_xsdata.py
sgr_library/data_classes/__init__.py
sgr_library/data_classes/ei_contacts/__init__.py
sgr_library/data_classes/ei_contacts/sgr_contacts_device_frame.py
sgr_library/data_classes/ei_gen_serial_int/__init__.py
sgr_library/data_classes/ei_gen_serial_int/sgr_serial_int_capability.py
sgr_library/data_classes/ei_gen_tcp_ip/__init__.py
sgr_library/data_classes/ei_gen_tcp_ip/sgr_tsp_srv_tcp_ip.py
sgr_library/data_classes/ei_modbus/__init__.py
sgr_library/data_classes/ei_modbus/sgr_modbus_eiconfigurator.py
sgr_library/data_classes/ei_modbus/sgr_modbus_eidata_types.py
sgr_library/data_classes/ei_modbus/sgr_modbus_eidevice_frame.py
sgr_library/data_classes/ei_modbus/sgr_modbus_helpers.py
sgr_library/data_classes/ei_rest_api/__init__.py
sgr_library/data_classes/ei_rest_api/sgr_rest_api_eidata_types.py
sgr_library/data_classes/ei_rest_api/sgr_rest_api_eidevice_frame.py
sgr_library/data_classes/generic/__init__.py
sgr_library/data_classes/generic/sgr_gen_data_point_definition.py
sgr_library/data_classes/generic/sgr_gen_device_frame.py
sgr_library/data_classes/generic/sgr_gen_device_profile.py
sgr_library/data_classes/generic/sgr_gen_functional_profile_definition.py
sgr_library/data_classes/generic/sgr_gen_type_definitions.py
sgr_library/data_classes/generic/sgr_manufacturer_list.py
sgr_demo_v0.0.1-0.0.1.dist-info/LICENSE.md
sgr_demo_v0.0.1-0.0.1.dist-info/METADATA
sgr_demo_v0.0.1-0.0.1.dist-info/WHEEL
sgr_demo_v0.0.1-0.0.1.dist-info/top_level.txt
sgr_demo_v0.0.1-0.0.1.dist-info/RECORD
